adv_lib/__init__.py
adv_lib/attacks/__init__.py
adv_lib/attacks/augmented_lagrangian.py
adv_lib/attacks/auto_pgd.py
adv_lib/attacks/boundary_projection_tf.py
adv_lib/attacks/decoupled_direction_norm.py
adv_lib/attacks/fast_minimum_norm.py
adv_lib/attacks/primal_dual_gradient_descent.py
adv_lib/attacks/projected_gradient_descent.py
adv_lib/attacks/self_adaptive_norm_update.py
adv_lib/attacks/sigma_zero.py
adv_lib/attacks/stochastic_sparse_attacks.py
adv_lib/attacks/structured_adversarial_attack.py
adv_lib/attacks/trust_region.py
adv_lib/attacks/carlini_wagner/__init__.py
adv_lib/attacks/carlini_wagner/l2.py
adv_lib/attacks/carlini_wagner/linf.py
adv_lib/attacks/fast_adaptive_boundary/__init__.py
adv_lib/attacks/fast_adaptive_boundary/fast_adaptive_boundary.py
adv_lib/attacks/fast_adaptive_boundary/projections.py
adv_lib/attacks/perceptual_color_attacks/__init__.py
adv_lib/attacks/perceptual_color_attacks/differential_color_functions.py
adv_lib/attacks/perceptual_color_attacks/perceptual_color_distance_al.py
adv_lib/attacks/segmentation/__init__.py
adv_lib/attacks/segmentation/alma_prox.py
adv_lib/attacks/segmentation/asma.py
adv_lib/attacks/segmentation/dense_adversary.py
adv_lib/attacks/segmentation/primal_dual_gradient_descent.py
adv_lib/distances/__init__.py
adv_lib/distances/color_difference.py
adv_lib/distances/lp_norms.py
adv_lib/distances/lpips.py
adv_lib/distances/structural_similarity.py
adv_lib/utils/__init__.py
adv_lib/utils/attack_utils.py
adv_lib/utils/color_conversions.py
adv_lib/utils/image_selection.py
adv_lib/utils/losses.py
adv_lib/utils/projections.py
adv_lib/utils/utils.py
adv_lib/utils/visdom_logger.py
adv_lib/utils/lagrangian_penalties/__init__.py
adv_lib/utils/lagrangian_penalties/all_penalties.py
adv_lib/utils/lagrangian_penalties/penalty_functions.py
adv_lib/utils/lagrangian_penalties/univariate_functions.py
adv_lib/utils/lagrangian_penalties/scripts/plot_penalties.py
adv_lib/utils/lagrangian_penalties/scripts/plot_univariates.py
adv_lib-0.2.2.dist-info/LICENSE
adv_lib-0.2.2.dist-info/METADATA
adv_lib-0.2.2.dist-info/WHEEL
adv_lib-0.2.2.dist-info/top_level.txt
adv_lib-0.2.2.dist-info/RECORD
