Metadata-Version: 2.1
Name: adv-lib
Version: 0.2.2
Summary: Library of various adversarial attacks resources in PyTorch
Author-email: Jerome Rony <jerome.rony@gmail.com>
License: BSD 3-Clause License
Project-URL: Repository, https://github.com/jeromerony/adversarial-library.git
Classifier: Programming Language :: Python :: 3
Classifier: Development Status :: 3 - Alpha
Classifier: Intended Audience :: Developers
Classifier: Intended Audience :: Science/Research
Classifier: Topic :: Scientific/Engineering :: Artificial Intelligence
Requires-Python: >=3.8
License-File: LICENSE
Requires-Dist: torch >=1.8.0
Requires-Dist: torchvision >=0.9.0
Requires-Dist: tqdm >=4.48.0
Requires-Dist: visdom >=0.1.8
Provides-Extra: test
Requires-Dist: scikit-image ; extra == 'test'
Requires-Dist: pytest ; extra == 'test'
